mediqaws_secrets_manager/__init__.py
mediqaws_secrets_manager-0.1.0.dist-info/LICENSE
mediqaws_secrets_manager-0.1.0.dist-info/METADATA
mediqaws_secrets_manager-0.1.0.dist-info/WHEEL
mediqaws_secrets_manager-0.1.0.dist-info/top_level.txt
mediqaws_secrets_manager-0.1.0.dist-info/RECORD
